IcingaDirectorAPI/__init__.py
IcingaDirectorAPI/base.py
IcingaDirectorAPI/director.py
IcingaDirectorAPI/exceptions.py
IcingaDirectorAPI/objects.py
icingadirectorapi-1.0.7.dist-info/METADATA
icingadirectorapi-1.0.7.dist-info/WHEEL
icingadirectorapi-1.0.7.dist-info/licenses/LICENSE
icingadirectorapi-1.0.7.dist-info/RECORD
