Metadata-Version: 2.1
Name: IcingaDirectorAPI
Version: 1.0.7
Summary: Python library for the Icinga Director RESTful API
Project-URL: Homepage, https://github.com/OffbeatFocus/IcingaDirectorAPI
Project-URL: Bug Tracker, https://github.com/OffbeatFocus/IcingaDirectorAPI/issues
Author-email: Offbeat Focus <offbeatfocus@protonmail.com>
License-File: LICENSE
Classifier: License :: OSI Approved :: GNU General Public License v3 (GPLv3)
Classifier: Operating System :: OS Independent
Classifier: Programming Language :: Python :: 3
Requires-Python: >=3.6
